ray_velda/__init__.py
ray_velda/command_runner.py
ray_velda/node_provider.py
ray_velda-0.1.1.dist-info/licenses/LICENSE
ray_velda-0.1.1.dist-info/METADATA
ray_velda-0.1.1.dist-info/WHEEL
ray_velda-0.1.1.dist-info/top_level.txt
ray_velda-0.1.1.dist-info/RECORD
