Metadata-Version: 2.4
Name: ray-velda
Version: 0.1.1
Summary: Ray node autoscaler based on Velda
Project-URL: Homepage, https://example.local/
Requires-Python: >=3.8
License-File: LICENSE
Requires-Dist: ray>=2.8
Dynamic: license-file
